{
  "benchmark": "SH000300",
  "candidate_decision": {
    "avg_cash_ratio_vs_no_model_delta": 0.019536793367533556,
    "candidate_decision_reason": "selection_checks_not_met",
    "candidate_for_future_final_test": false,
    "pass_worst_year_drawdown": true,
    "positive_valid_years": 1,
    "qualified_valid_years": 1,
    "stop_time_ratio_reduction": -0.02119999999999988,
    "trade_ratio_vs_no_model": 0.7246376811594203,
    "year_return_concentration": 1.0
  },
  "candidate_for_future_final_test": false,
  "candidate_level_replay": "100 shares at T+1 open, same stop/exit/cost rules, no portfolio constraints",
  "candidate_pool_audit_rows": 40,
  "class_imbalance": {
    "class_weight_cap": 10.0,
    "use_scale_pos_weight_when_bad_minority": true
  },
  "config_path": "Explore6/configs/meta_label_v1.yaml",
  "config_sha256": "92931a0afd510bad87968ca3a02a11c8f7e2480004291871dfa24337882d86c6",
  "explore5_config_paths_rewritten": true,
  "explore5_result_csv_used_for_features": false,
  "explore5_result_csv_used_for_label": false,
  "explore5_result_csv_used_for_replay": false,
  "feature_columns": [
    "trend_score",
    "trend_score_pct",
    "candidate_rank",
    "distance_to_ema20",
    "distance_to_ema60",
    "pullback_depth",
    "money_ratio20",
    "volume_ratio20",
    "money_zscore20",
    "money_change5",
    "money_change20",
    "ret5",
    "ret20",
    "ret60",
    "volatility20",
    "atr20_ratio",
    "ema20_slope20",
    "ema60_slope20",
    "distance_to_high60",
    "distance_to_low20",
    "close_gt_ema60_ratio",
    "ema20_gt_ema60_ratio",
    "raw_pullback_shape_numeric",
    "raw_pullback_candidate_numeric",
    "rule_pullback_entry_numeric",
    "gate_applicable_numeric",
    "market_ok_numeric",
    "width_ok_numeric",
    "industry_trend_ok_numeric",
    "pullback_money_weak_numeric",
    "pullback_top10_20_numeric"
  ],
  "fold_sample_sufficiency": [
    {
      "bad_trade_count": 6225,
      "fold": "WF1",
      "good_or_neutral_count": 2328,
      "low_sample_warning": false,
      "min_class_count": 30,
      "min_train_labeled_candidates": 100,
      "minority_class_ratio": 0.27218519817607856,
      "skip_reason": "",
      "status": "trainable",
      "target_train_labeled_candidates": 200,
      "train_end": "2018-12-31",
      "train_labeled_candidates": 8553,
      "train_start": "2017-01-01",
      "trainable": true
    },
    {
      "bad_trade_count": 9567,
      "fold": "WF2",
      "good_or_neutral_count": 3522,
      "low_sample_warning": false,
      "min_class_count": 30,
      "min_train_labeled_candidates": 100,
      "minority_class_ratio": 0.26908090763236303,
      "skip_reason": "",
      "status": "trainable",
      "target_train_labeled_candidates": 200,
      "train_end": "2019-12-31",
      "train_labeled_candidates": 13089,
      "train_start": "2017-01-01",
      "trainable": true
    },
    {
      "bad_trade_count": 13200,
      "fold": "WF3",
      "good_or_neutral_count": 4971,
      "low_sample_warning": false,
      "min_class_count": 30,
      "min_train_labeled_candidates": 100,
      "minority_class_ratio": 0.2735677728248308,
      "skip_reason": "",
      "status": "trainable",
      "target_train_labeled_candidates": 200,
      "train_end": "2020-12-31",
      "train_labeled_candidates": 18171,
      "train_start": "2017-01-01",
      "trainable": true
    },
    {
      "bad_trade_count": 16466,
      "fold": "WF4",
      "good_or_neutral_count": 6151,
      "low_sample_warning": false,
      "min_class_count": 30,
      "min_train_labeled_candidates": 100,
      "minority_class_ratio": 0.2719635672281912,
      "skip_reason": "",
      "status": "trainable",
      "target_train_labeled_candidates": 200,
      "train_end": "2021-12-31",
      "train_labeled_candidates": 22617,
      "train_start": "2017-01-01",
      "trainable": true
    },
    {
      "bad_trade_count": 19656,
      "fold": "WF5",
      "good_or_neutral_count": 6902,
      "low_sample_warning": false,
      "min_class_count": 30,
      "min_train_labeled_candidates": 100,
      "minority_class_ratio": 0.2598840274117027,
      "skip_reason": "",
      "status": "trainable",
      "target_train_labeled_candidates": 200,
      "train_end": "2022-12-31",
      "train_labeled_candidates": 26558,
      "train_start": "2017-01-01",
      "trainable": true
    }
  ],
  "folds": [
    {
      "fold": "WF1",
      "train_end": "2018-12-31",
      "train_start": "2017-01-01",
      "valid_end": "2020-12-31",
      "valid_start": "2019-01-01"
    },
    {
      "fold": "WF2",
      "train_end": "2019-12-31",
      "train_start": "2017-01-01",
      "valid_end": "2021-12-31",
      "valid_start": "2020-01-01"
    },
    {
      "fold": "WF3",
      "train_end": "2020-12-31",
      "train_start": "2017-01-01",
      "valid_end": "2022-12-31",
      "valid_start": "2021-01-01"
    },
    {
      "fold": "WF4",
      "train_end": "2021-12-31",
      "train_start": "2017-01-01",
      "valid_end": "2023-12-31",
      "valid_start": "2022-01-01"
    },
    {
      "fold": "WF5",
      "train_end": "2022-12-31",
      "train_start": "2017-01-01",
      "valid_end": "2024-12-31",
      "valid_start": "2023-01-01"
    }
  ],
  "industry_membership_point_in_time": false,
  "industry_membership_source": "Explore4/data/targets/industry_membership.csv",
  "inner_selection": [
    {
      "fold": "WF1",
      "inner_fit_end": "2017-12-31",
      "inner_fit_samples": 5675,
      "inner_fit_start": "2017-01-01",
      "inner_method": "first_year_fit_second_year_select",
      "inner_select_bad": 2185,
      "inner_select_end": "2018-12-31",
      "inner_select_good": 364,
      "inner_select_samples": 2549,
      "inner_select_start": "2018-01-01",
      "selected_param_id": "lgbm_01",
      "selected_threshold": 0.5,
      "selection_mode": "eligible",
      "skip_reason": "",
      "trainable": true
    },
    {
      "fold": "WF2",
      "inner_fit_end": "2018-12-31",
      "inner_fit_samples": 8553,
      "inner_fit_start": "2017-01-01",
      "inner_method": "expanding_last_year_select",
      "inner_select_bad": 3291,
      "inner_select_end": "2019-12-31",
      "inner_select_good": 1156,
      "inner_select_samples": 4447,
      "inner_select_start": "2019-01-01",
      "selected_param_id": "lgbm_06",
      "selected_threshold": 0.6,
      "selection_mode": "eligible",
      "skip_reason": "",
      "trainable": true
    },
    {
      "fold": "WF3",
      "inner_fit_end": "2019-12-31",
      "inner_fit_samples": 13089,
      "inner_fit_start": "2017-01-01",
      "inner_method": "expanding_last_year_select",
      "inner_select_bad": 3425,
      "inner_select_end": "2020-12-31",
      "inner_select_good": 1214,
      "inner_select_samples": 4639,
      "inner_select_start": "2020-01-01",
      "selected_param_id": "lgbm_06",
      "selected_threshold": 0.55,
      "selection_mode": "eligible",
      "skip_reason": "",
      "trainable": true
    },
    {
      "fold": "WF4",
      "inner_fit_end": "2020-12-31",
      "inner_fit_samples": 18171,
      "inner_fit_start": "2017-01-01",
      "inner_method": "expanding_last_year_select",
      "inner_select_bad": 3194,
      "inner_select_end": "2021-12-31",
      "inner_select_good": 924,
      "inner_select_samples": 4118,
      "inner_select_start": "2021-01-01",
      "selected_param_id": "lgbm_01",
      "selected_threshold": 0.5,
      "selection_mode": "eligible",
      "skip_reason": "",
      "trainable": true
    },
    {
      "fold": "WF5",
      "inner_fit_end": "2021-12-31",
      "inner_fit_samples": 22617,
      "inner_fit_start": "2017-01-01",
      "inner_method": "expanding_last_year_select",
      "inner_select_bad": 2969,
      "inner_select_end": "2022-12-31",
      "inner_select_good": 634,
      "inner_select_samples": 3603,
      "inner_select_start": "2022-01-01",
      "selected_param_id": "lgbm_01",
      "selected_threshold": 0.5,
      "selection_mode": "eligible",
      "skip_reason": "",
      "trainable": true
    }
  ],
  "label_definition": {
    "amount": 100,
    "bad_exit_reasons": [
      "stop_loss",
      "time_stop"
    ],
    "bad_r_multiple_threshold": -0.5,
    "bad_return_threshold": -0.02,
    "entry_type": "pullback",
    "good_exit_reasons": [
      "trailing_stop"
    ],
    "good_r_multiple_threshold": 1.0,
    "good_return_threshold": 0.03
  },
  "label_rows": 39279,
  "lgbm_final_model_stop_reason": "",
  "lgbm_final_model_stopped": false,
  "lgbm_param_grid": [
    {
      "feature_fraction": 0.7,
      "id": "lgbm_01",
      "lambda_l1": 0,
      "lambda_l2": 10,
      "learning_rate": 0.03,
      "min_data_in_leaf": 20,
      "num_leaves": 15
    },
    {
      "feature_fraction": 0.9,
      "id": "lgbm_02",
      "lambda_l1": 10,
      "lambda_l2": 50,
      "learning_rate": 0.03,
      "min_data_in_leaf": 50,
      "num_leaves": 15
    },
    {
      "feature_fraction": 0.9,
      "id": "lgbm_03",
      "lambda_l1": 0,
      "lambda_l2": 50,
      "learning_rate": 0.05,
      "min_data_in_leaf": 20,
      "num_leaves": 15
    },
    {
      "feature_fraction": 0.7,
      "id": "lgbm_04",
      "lambda_l1": 10,
      "lambda_l2": 10,
      "learning_rate": 0.05,
      "min_data_in_leaf": 50,
      "num_leaves": 15
    },
    {
      "feature_fraction": 0.9,
      "id": "lgbm_05",
      "lambda_l1": 10,
      "lambda_l2": 10,
      "learning_rate": 0.03,
      "min_data_in_leaf": 20,
      "num_leaves": 31
    },
    {
      "feature_fraction": 0.7,
      "id": "lgbm_06",
      "lambda_l1": 0,
      "lambda_l2": 50,
      "learning_rate": 0.03,
      "min_data_in_leaf": 50,
      "num_leaves": 31
    },
    {
      "feature_fraction": 0.7,
      "id": "lgbm_07",
      "lambda_l1": 10,
      "lambda_l2": 50,
      "learning_rate": 0.05,
      "min_data_in_leaf": 20,
      "num_leaves": 31
    },
    {
      "feature_fraction": 0.9,
      "id": "lgbm_08",
      "lambda_l1": 0,
      "lambda_l2": 10,
      "learning_rate": 0.05,
      "min_data_in_leaf": 50,
      "num_leaves": 31
    }
  ],
  "market": "mcap500_mainboard_20251231",
  "meta_label_dataset_rows": 139767,
  "observed_replication_used_for_selection": false,
  "output_paths": [
    "Explore6/outputs/cache/stock_indicators.pkl",
    "Explore6/outputs/cache/stock_signals.pkl",
    "Explore6/outputs/reports/candidate_label_replay.csv",
    "Explore6/outputs/reports/candidate_pool_audit.csv",
    "Explore6/outputs/reports/class_imbalance_audit.csv",
    "Explore6/outputs/reports/explore6_meta_label_report.md",
    "Explore6/outputs/reports/feature_audit.csv",
    "Explore6/outputs/reports/fold_execution_audit.csv",
    "Explore6/outputs/reports/fold_model_metrics.csv",
    "Explore6/outputs/reports/fold_portfolio_daily.csv",
    "Explore6/outputs/reports/fold_predictions.csv",
    "Explore6/outputs/reports/fold_replay_metrics.csv",
    "Explore6/outputs/reports/fold_threshold_selection.csv",
    "Explore6/outputs/reports/fold_trade_detail.csv",
    "Explore6/outputs/reports/generated_daily_candidates.csv",
    "Explore6/outputs/reports/generated_industry_regime.csv",
    "Explore6/outputs/reports/generated_market_regime.csv",
    "Explore6/outputs/reports/generated_market_width.csv",
    "Explore6/outputs/reports/generated_signals.csv",
    "Explore6/outputs/reports/generated_theme_regime.csv",
    "Explore6/outputs/reports/inner_oof_predictions.csv",
    "Explore6/outputs/reports/inner_selection_audit.csv",
    "Explore6/outputs/reports/label_audit.csv",
    "Explore6/outputs/reports/label_generation_audit.csv",
    "Explore6/outputs/reports/meta_label_dataset.csv",
    "Explore6/outputs/reports/no_model_gate_portfolio_daily.csv",
    "Explore6/outputs/reports/no_model_gate_trade_detail.csv",
    "Explore6/outputs/reports/observed_replication_summary.csv",
    "Explore6/outputs/reports/sample_sufficiency_audit.csv",
    "Explore6/outputs/reports/source_data_audit.csv",
    "Explore6/outputs/reports/trade_failure_attribution.csv",
    "Explore6/outputs/reports/year_metrics.csv"
  ],
  "provider_uri": "Explore1/data/qlib/cn_data",
  "report_conclusion": "没有形成 Explore6 候选版本。",
  "required_fields": [
    "$open",
    "$high",
    "$low",
    "$close",
    "$volume",
    "$money",
    "$factor"
  ],
  "self_test_passed": true,
  "source_background_report": "Explore5/outputs/reports/explore5_final_report.md",
  "source_background_report_sha256": "d11f13ab14b986f8d6a265b67711b408a225dcb83b2e2e91d2eb49ec0a5495c6",
  "source_rule_config": "Explore4/configs/trend_rule_v1_frozen.yaml",
  "source_rule_config_sha256": "5e8ba37a8ce98ee3efb18139e5e1c0aa1859fd85e0a3df2e0e05872cbc27f3c7",
  "source_walk_forward_config": "Explore5/configs/walk_forward_v1.yaml",
  "source_walk_forward_config_sha256": "898ee7b7334b6ef8c3b424e51ba9a1ebec2f1a366c2b858ffb9091b7f29a3a59",
  "threshold_candidates": [
    0.5,
    0.55,
    0.6,
    0.65,
    0.7
  ],
  "trainable_lgbm_folds": 5,
  "universe_asof_date": "2025-12-31",
  "universe_point_in_time": false,
  "universe_source": "Explore1/data/universe/mcap500_mainboard_20251231.csv"
}
